EnclaveSDK/__init__.py
EnclaveSDK/api_client.py
EnclaveSDK/api_response.py
EnclaveSDK/configuration.py
EnclaveSDK/exceptions.py
EnclaveSDK/py.typed
EnclaveSDK/rest.py
EnclaveSDK/api/__init__.py
EnclaveSDK/api/auth_api.py
EnclaveSDK/api/data_api.py
EnclaveSDK/api/escrow_api.py
EnclaveSDK/api/log_api.py
EnclaveSDK/api/mlflow_api.py
EnclaveSDK/api/report_api.py
EnclaveSDK/api/run_api.py
EnclaveSDK/models/__init__.py
EnclaveSDK/models/algorithm_status.py
EnclaveSDK/models/api_v1_data_files_get200_response.py
EnclaveSDK/models/api_v1_log_post200_response.py
EnclaveSDK/models/artifact_response.py
EnclaveSDK/models/auth_request.py
EnclaveSDK/models/basic_message.py
EnclaveSDK/models/file.py
EnclaveSDK/models/log_data.py
EnclaveSDK/models/ping_attestation_status.py
EnclaveSDK/models/ping_enclave_status.py
EnclaveSDK/models/ping_escrow_status.py
EnclaveSDK/models/ping_key_manager_status.py
EnclaveSDK/models/report.py
EnclaveSDK/models/report_json_schema.py
EnclaveSDK/models/request_file_data.py
EnclaveSDK/models/sas_object.py
EnclaveSDK/models/server_config.py
EnclaveSDK/models/sql_query.py
EnclaveSDK/models/sql_response.py
EnclaveSDK/models/validation_result.py
EnclaveSDK-1.5.9.dist-info/METADATA
EnclaveSDK-1.5.9.dist-info/WHEEL
EnclaveSDK-1.5.9.dist-info/top_level.txt
EnclaveSDK-1.5.9.dist-info/RECORD
