Metadata-Version: 2.1
Name: EnclaveSDK
Version: 1.5.9
Summary: BeeKeeperAI EscrowAI Enclave API
Home-page: 
Author: OpenAPI Generator community
Author-email: engineering@beekeeperai.com
Keywords: OpenAPI,OpenAPI-Generator,BeeKeeperAI EscrowAI Enclave API
Requires-Dist: urllib3 <3.0.0,>=1.25.3
Requires-Dist: python-dateutil >=2.8.2
Requires-Dist: pydantic >=2
Requires-Dist: typing-extensions >=4.7.1
